{"cameraMode":{"drawMode":0,"name":"Shaded","section":"Shading Mode"},"sceneLighting":true,"audioPlay":false,"sceneViewState":{"m_AlwaysRefresh":false,"showFog":true,"showSkybox":true,"showFlares":true,"showImageEffects":true,"showParticleSystems":true,"showVisualEffectGraphs":true,"m_FxEnabled":true},"in2DMode":false,"pivot":{"x":2.9657366275787355,"y":9.9923677444458,"z":54.27742004394531},"rotation":{"x":-0.11303261667490006,"y":-0.13312363624572755,"z":0.015283730812370777,"w":-0.9845193028450012},"size":13.891345024108887,"orthographic":false}